[
  {
    "id": 1,
    "brand": "NIVIA",
    "name": "Urban Explorer Backpack",
    "image": "https://vidamik.com/_next/image?url=https%3A%2F%2Fcdn.shopify.com%2Fs%2Ffiles%2F1%2F0589%2F7492%2F8989%2Ffiles%2F85cc58608bf138a50036bcfe86a3a362_ce4cf063-8ef7-4e8d-b994-cefb291e4377.jpg%3Fv%3D1712760391&w=1080&q=75",
    "price": 65.00,
    "category": "Backpack"
  },
  {
    "id": 2,
    "brand": "ADIDAS",
    "name": "Classic Backpack",
    "image": "https://vidamik.com/_next/image?url=https%3A%2F%2Fcdn.shopify.com%2Fs%2Ffiles%2F1%2F0589%2F7492%2F8989%2Ffiles%2F8072c8b5718306d4be25aac21836ce16.jpg%3Fv%3D1712758711&w=1080&q=75",
    "price": 55.00,
    "category": "Backpack"
  },
  {
    "id": 3,
    "brand": "ADIDAS",
    "name": "Classic Backpack | Legend Ink",
    "image": "https://outerreaches.ca/cdn/shop/files/7883dc186e15bf29dad696e1e989e914_1024x1024.jpg?v=1730906224",
    "price": 95.00,
    "category": "Shoes"
  },
  {
    "id": 4,
    "brand": "ADIDAS",
    "name": "Kids Stan Smith",
    "image": "https://vidamik.com/_next/image?url=https%3A%2F%2Fcdn.shopify.com%2Fs%2Ffiles%2F1%2F0589%2F7492%2F8989%2Ffiles%2F44694ee386818f3276566210464cf341.jpg%3Fv%3D1712758597&w=1080&q=75",
    "price": 65.00,
    "category": "Shoes"
  },
  {
    "id": 5,
    "brand": "ADIDAS",
    "name": "Superstar 80s",
    "image": "https://www.workingclassheroes.co.uk/images/products/archive/g/ge/gellytevblkblu.jpg?width=1998&height=1998&quality=85&mode=pad&format=webp&bgcolor=ffffff",
    "price": 55.00,
    "category": "Shoes"
  },
  {
    "id": 6,
    "brand": "ADIDAS",
    "name": "Kid's Sprint Sneakers",
    "image": "https://extrabutterny.com/cdn/shop/products/DN6K4-9090_1.jpg?v=1478357149&width=816",
    "price": 95.00,
    "category": "Shoes"
  },
  {
    "id": 7,
    "brand": "ASICS TIGER",
    "name": "GEL-LYTE V '30 YEARS OF GEL'",
    "image": "https://india.robinstore.co/cdn/shop/products/23550440c4ccab05e4fc1ebd85e742cc_grande.jpg?v=1618565979",
    "price": 65.00,
    "category": "Shoes"
  },
  {
    "id": 8,
    "brand": "HERSCHEL",
    "name": "IONA",
    "image": "https://www.overkillshop.com/cdn/shop/files/10331-00001-os_01.jpg?v=1715995788&width=5000",
    "price": 55.00,
    "category": "Backpack"
  },
  {
    "id": 9,
    "brand": "ADIDAS",
    "name": "Kid's Sprint Sneakers",
    "image": "https://teststore.littledata.io/cdn/shop/products/401f6d6c355012d9eb8749feda025256_540x.jpg?v=1571736156",
    "price": 95.00,
    "category": "Shoes"
  }
]
